rwords/__init__.py
rwords/commands.py
rwords/console.py
rwords/models.py
rwords/review_arithmetic.py
rwords/rw.py
rwords/store.py
rwords/words.py
rwords/core/__init__.py
rwords/core/db.py
rwords/core/exception.py
rwords/core/iciba_word_api.py
rwords/core/settings.py
rwords/core/utills.py
rwords/data/__init__.py
rwords/data/db/__init__.py
rwords/data/mp3/__init__.py
rwords-0.0.0rc106.dist-info/LICENSE
rwords-0.0.0rc106.dist-info/METADATA
rwords-0.0.0rc106.dist-info/WHEEL
rwords-0.0.0rc106.dist-info/entry_points.txt
rwords-0.0.0rc106.dist-info/top_level.txt
rwords-0.0.0rc106.dist-info/RECORD
