Metadata-Version: 2.1
Name: rwords
Version: 0.0.0rc106
Summary: Rwords: A command line tool to help you remember words faster.
Home-page: UNKNOWN
Author: endlex
Author-email: endlex@aliyun.com
License: MIT
Platform: UNKNOWN
Requires-Python: >=2.7, !=3.0.*, !=3.1.*, !=3.2.*, !=3.3.*
Requires-Dist: docopt
Requires-Dist: requests (>2.0)
Requires-Dist: sqlalchemy (>=1.2)
Requires-Dist: readchar
Requires-Dist: pygame (>=1.6)
